LICENSE
MANIFEST.in
README.rst
VERSION
setup.cfg
setup.py
src/sagemaker_mxnet_container/__init__.py
src/sagemaker_mxnet_container/training.py
src/sagemaker_mxnet_container/training_utils.py
src/sagemaker_mxnet_training.egg-info/PKG-INFO
src/sagemaker_mxnet_training.egg-info/SOURCES.txt
src/sagemaker_mxnet_training.egg-info/dependency_links.txt
src/sagemaker_mxnet_training.egg-info/requires.txt
src/sagemaker_mxnet_training.egg-info/top_level.txt