Metadata-Version: 2.1
Name: sagemaker-mxnet-training
Version: 3.1.6
Summary: Open source library for creating MXNet containers to run on Amazon SageMaker.
Home-page: https://github.com/aws/sagemaker-mxnet-containers
Author: Amazon Web Services
License: Apache License 2.0
Platform: UNKNOWN
Classifier: Development Status :: 5 - Production/Stable
Classifier: Intended Audience :: Developers
Classifier: Natural Language :: English
Classifier: License :: OSI Approved :: Apache Software License
Classifier: Programming Language :: Python
Classifier: Programming Language :: Python :: 2.7
Classifier: Programming Language :: Python :: 3.5
Provides-Extra: test
